{
    "cv2products": [
        {
            "id": 5,
            "name": "Environment and Sustainability",
            "desc": "Civil | Mechanical | I.T | Electrical",
            "size": "10mb",
            "sem": "2nd-Sem",
            "durl": "https://drive.google.com/uc?export=download&id=1HkOUzKyz7bliRhnrsY_gjHHUm_LtWRNo",
            "surl": "https://drive.google.com/uc?export=download&id=1Dh9C0ytEr2icrx8crlm2lLiv1YqH3p_O",
            "lpurl": "https://drive.google.com/uc?export=download&id=",
            "purl": "https://drive.google.com/uc?export=download&id=",
            "image": "https://neo2708.github.io/pic.github.io/005.png"
        },
        {
            "id": 25,
            "name": "Applied Mathematics",
            "desc": "Civil | Mechanical",
            "size": "10mb",
            "sem": "Sem-2",
            "durl": "https://drive.google.com/uc?export=download&id=1HkOUzKyz7bliRhnrsY_gjHHUm_LtWRNo",
            "surl": "https://drive.google.com/uc?export=download&id=1Dh9C0ytEr2icrx8crlm2lLiv1YqH3p_O",
            "lpurl": "https://drive.google.com/uc?export=download&id=",
            "purl": "https://drive.google.com/uc?export=download&id=",
            "image": "https://neo2708.github.io/pic.github.io/025.png"
        },
        {
            "id": 26,
            "name": "Engineering Mechanics",
            "desc": "Civil | Mechanical",
            "size": "10mb",
            "sem": "Sem-2",
            "durl": "https://drive.google.com/uc?export=download&id=1HkOUzKyz7bliRhnrsY_gjHHUm_LtWRNo",
            "surl": "https://drive.google.com/uc?export=download&id=1Dh9C0ytEr2icrx8crlm2lLiv1YqH3p_O",
            "lpurl": "https://drive.google.com/uc?export=download&id=",
            "purl": "https://drive.google.com/uc?export=download&id=",
            "image": "https://neo2708.github.io/pic.github.io/026.png"
        }
    ]
}